numtools/__init__.py
numtools/csyslib.py
numtools/intzip.py
numtools/misc.py
numtools/pandas_tk.py
numtools/serializer.py
numtools/vgextended.py
numtools-3.1.0.dist-info/LICENSE
numtools-3.1.0.dist-info/METADATA
numtools-3.1.0.dist-info/WHEEL
numtools-3.1.0.dist-info/RECORD
