Metadata-Version: 2.1
Name: numtools
Version: 3.1.0
Summary: numeric-gmbH toolbox
Author: numenic
Author-email: nicolas@cordier.io
Requires-Python: >=3.10,<3.12
Classifier: Programming Language :: Python :: 3
Classifier: Programming Language :: Python :: 3.10
Classifier: Programming Language :: Python :: 3.11
Requires-Dist: networkx
Requires-Dist: numpy (>=1,<2)
Requires-Dist: pandas[performance] (>=2.0,<3.0)
Requires-Dist: vg (>=2.0,<3.0)
